{
  "condition_id": "0xf7ebedeb7bf972eff320e928160fe24d2f97658ca2bd39476ec0a0a56d4b0a26",
  "event_id": "495650",
  "fetch_status": "ok",
  "fetched_at": "2026-06-07T03:14:47+00:00",
  "http_status": 200,
  "market_id": "2286430",
  "question": "Dota 2: Team Spirit vs BetBoom Team - Game 2 Winner",
  "raw_response": {
    "history": [
      {
        "p": 0.555,
        "t": 1779051615
      },
      {
        "p": 0.57,
        "t": 1779055208
      },
      {
        "p": 0.58,
        "t": 1779058809
      },
      {
        "p": 0.56,
        "t": 1779062413
      },
      {
        "p": 0.56,
        "t": 1779066007
      },
      {
        "p": 0.555,
        "t": 1779069606
      },
      {
        "p": 0.555,
        "t": 1779073210
      },
      {
        "p": 0.555,
        "t": 1779076806
      },
      {
        "p": 0.555,
        "t": 1779080420
      },
      {
        "p": 0.555,
        "t": 1779084011
      },
      {
        "p": 0.555,
        "t": 1779087607
      },
      {
        "p": 0.545,
        "t": 1779091206
      },
      {
        "p": 0.545,
        "t": 1779094808
      },
      {
        "p": 0.545,
        "t": 1779098408
      },
      {
        "p": 0.545,
        "t": 1779102006
      },
      {
        "p": 0.545,
        "t": 1779105611
      },
      {
        "p": 0.545,
        "t": 1779109206
      },
      {
        "p": 0.545,
        "t": 1779112809
      },
      {
        "p": 0.545,
        "t": 1779116408
      },
      {
        "p": 0.545,
        "t": 1779120006
      },
      {
        "p": 0.545,
        "t": 1779123608
      },
      {
        "p": 0.545,
        "t": 1779127209
      },
      {
        "p": 0.545,
        "t": 1779130810
      },
      {
        "p": 0.545,
        "t": 1779134419
      },
      {
        "p": 0.545,
        "t": 1779138008
      },
      {
        "p": 0.54,
        "t": 1779141607
      },
      {
        "p": 0.535,
        "t": 1779145207
      },
      {
        "p": 0.535,
        "t": 1779148810
      },
      {
        "p": 0.535,
        "t": 1779152406
      },
      {
        "p": 0.535,
        "t": 1779156004
      },
      {
        "p": 0.535,
        "t": 1779159609
      },
      {
        "p": 0.53,
        "t": 1779163207
      },
      {
        "p": 0.535,
        "t": 1779166806
      },
      {
        "p": 0.535,
        "t": 1779170408
      },
      {
        "p": 0.535,
        "t": 1779174005
      },
      {
        "p": 0.535,
        "t": 1779177604
      },
      {
        "p": 0.535,
        "t": 1779181210
      },
      {
        "p": 0.535,
        "t": 1779184805
      },
      {
        "p": 0.535,
        "t": 1779188409
      },
      {
        "p": 0.535,
        "t": 1779192026
      },
      {
        "p": 0.535,
        "t": 1779195608
      },
      {
        "p": 0.545,
        "t": 1779199208
      },
      {
        "p": 0.55,
        "t": 1779202811
      },
      {
        "p": 0.735,
        "t": 1779206408
      },
      {
        "p": 0.9995,
        "t": 1779210012
      },
      {
        "p": 0.9995,
        "t": 1779213608
      }
    ]
  },
  "requested_end_ts": "1779216449",
  "requested_fidelity": "60",
  "requested_interval": "all",
  "requested_start_ts": "1779047313",
  "slug": "dota2-ts8-bb4-2026-05-19-game2",
  "source_universe": "polymarket_public_search",
  "token_id": "44677125839440747598128223878929934156740695228430650465466409162095539417623"
}