{
  "condition_id": "0xe659dcd521d82bd17d48bc56deee329b620feb9fe6f5efe9bf9eb75834f6f54a",
  "event_id": "554286",
  "fetch_status": "ok",
  "fetched_at": "2026-06-07T01:22:47+00:00",
  "http_status": 200,
  "market_id": "2425914",
  "question": "Dota 2: Rostikfacekid Club vs TPaBoMaH Club - Game 2 Winner",
  "raw_response": {
    "history": [
      {
        "p": 0.5,
        "t": 1780470008
      },
      {
        "p": 0.5,
        "t": 1780473607
      },
      {
        "p": 0.5,
        "t": 1780477214
      },
      {
        "p": 0.5,
        "t": 1780480807
      },
      {
        "p": 0.5,
        "t": 1780484409
      },
      {
        "p": 0.5,
        "t": 1780488009
      },
      {
        "p": 0.51,
        "t": 1780491608
      },
      {
        "p": 0.51,
        "t": 1780495206
      },
      {
        "p": 0.5,
        "t": 1780498809
      },
      {
        "p": 0.51,
        "t": 1780502406
      },
      {
        "p": 0.51,
        "t": 1780506008
      },
      {
        "p": 0.51,
        "t": 1780509609
      },
      {
        "p": 0.51,
        "t": 1780513204
      },
      {
        "p": 0.5,
        "t": 1780516804
      },
      {
        "p": 0.5,
        "t": 1780520408
      },
      {
        "p": 0.515,
        "t": 1780524010
      },
      {
        "p": 0.5,
        "t": 1780527605
      },
      {
        "p": 0.5,
        "t": 1780531206
      },
      {
        "p": 0.495,
        "t": 1780534807
      },
      {
        "p": 0.5,
        "t": 1780538404
      },
      {
        "p": 0.51,
        "t": 1780542009
      },
      {
        "p": 0.5,
        "t": 1780545606
      },
      {
        "p": 0.5,
        "t": 1780549205
      },
      {
        "p": 0.505,
        "t": 1780552804
      },
      {
        "p": 0.48,
        "t": 1780556406
      },
      {
        "p": 0.5,
        "t": 1780560005
      },
      {
        "p": 0.5,
        "t": 1780563605
      },
      {
        "p": 0.5,
        "t": 1780567205
      },
      {
        "p": 0.5,
        "t": 1780570805
      },
      {
        "p": 0.52,
        "t": 1780574407
      },
      {
        "p": 0.5,
        "t": 1780578004
      },
      {
        "p": 0.5,
        "t": 1780581607
      },
      {
        "p": 0.0045,
        "t": 1780585206
      },
      {
        "p": 0.0035,
        "t": 1780588805
      },
      {
        "p": 0.0035,
        "t": 1780592432
      },
      {
        "p": 0.0005,
        "t": 1780596006
      },
      {
        "p": 0.0005,
        "t": 1780599619
      },
      {
        "p": 0.0005,
        "t": 1780603205
      },
      {
        "p": 0.0005,
        "t": 1780606808
      }
    ]
  },
  "requested_end_ts": "1780608780",
  "requested_fidelity": "60",
  "requested_interval": "all",
  "requested_start_ts": "1780469089",
  "slug": "dota2-rostik-tpabom-2026-06-04-game2",
  "source_universe": "polymarket_event",
  "token_id": "44727898120204970582889014070145847262937185885952988474596445740064504848380"
}