{
  "condition_id": "0x42c8160e5c6a4e642d009cf021ce5f7500ed174dc12bfe13690932a0b51fc207",
  "event_id": "195358",
  "fetch_status": "ok",
  "fetched_at": "2026-06-07T07:51:23+00:00",
  "http_status": 200,
  "market_id": "1312808",
  "question": "Dota 2: Team TPaBoMaH vs Team 9pasha - Game 1 Winner",
  "raw_response": {
    "history": [
      {
        "p": 0.515,
        "t": 1769950824
      },
      {
        "p": 0.505,
        "t": 1769954450
      },
      {
        "p": 0.005,
        "t": 1769958040
      },
      {
        "p": 0.4955,
        "t": 1769961651
      },
      {
        "p": 0.4945,
        "t": 1769965223
      },
      {
        "p": 0.002,
        "t": 1769968826
      },
      {
        "p": 0.002,
        "t": 1769972424
      },
      {
        "p": 0.0005,
        "t": 1769976028
      }
    ]
  },
  "requested_end_ts": "1769977276",
  "requested_fidelity": "60",
  "requested_interval": "all",
  "requested_start_ts": "1769947352",
  "slug": "dota2-tpabo-9pas-2026-02-01-game1",
  "source_universe": "polymarket_public_search",
  "token_id": "6621567449445351255749612350061065462478890257688206197217845399345346025820"
}